DBDiscord/__init__.py
DBDiscord-1.0.1.dist-info/METADATA
DBDiscord-1.0.1.dist-info/WHEEL
DBDiscord-1.0.1.dist-info/top_level.txt
DBDiscord-1.0.1.dist-info/RECORD
