Metadata-Version: 2.1
Name: DBDiscord
Version: 1.0.1
Summary: A DB using discord's server, category, and textchannels.
Home-page: https://github.com/Tim232/DBDiscord
Author: Tim232
Author-email: endbot4023@gmail.com
License: GNU General Public License v3.0
Platform: UNKNOWN
Classifier: Programming Language :: Python :: 3
Classifier: License :: OSI Approved :: GNU Lesser General Public License v3 (LGPLv3)
Classifier: Operating System :: OS Independent
